teachmedijkstra/Constants.py
teachmedijkstra/Dijkstra.py
teachmedijkstra/DirectedGraph.py
teachmedijkstra/UndirectedGraph.py
teachmedijkstra/Utils.py
teachmedijkstra/__init__.py
teachmedijkstra-0.1.0.dist-info/LICENSE
teachmedijkstra-0.1.0.dist-info/METADATA
teachmedijkstra-0.1.0.dist-info/WHEEL
teachmedijkstra-0.1.0.dist-info/top_level.txt
teachmedijkstra-0.1.0.dist-info/RECORD
