Metadata-Version: 2.1
Name: teachmedijkstra
Version: 0.1.0
Summary: Demonstration of the Dijkstra algorithm for educational purposes
Home-page: https://gitlab.com/petrikm/teachmedijkstra
Author: Milan Petrík
Author-email: milan.petrik@protonmail.com
License: GPLv3
Keywords: Graph,Finding shortest path
Platform: UNKNOWN
Classifier: Development Status :: 4 - Beta
Classifier: Programming Language :: Python :: 3
Classifier: License :: OSI Approved :: GNU General Public License v3 (GPLv3)
Classifier: Operating System :: OS Independent
Classifier: Topic :: Education
Classifier: Intended Audience :: Education
Requires-Python: >=3.6
